easy_config_py/__init__.py
easy_config_py/addict.py
easy_config_py/config.py
easy_config_py/file_loader.py
easy_config_py-0.0.4.dist-info/METADATA
easy_config_py-0.0.4.dist-info/WHEEL
easy_config_py-0.0.4.dist-info/top_level.txt
easy_config_py-0.0.4.dist-info/RECORD
