Metadata-Version: 2.1
Name: easy-config-py
Version: 0.0.4
Home-page: https://github.com/cookieGeGe/py_easy_config
Author: cookieGeGe
Author-email: zhang1114570651@gmail.com
License: MIT
Keywords: easy,config,addict,anyconfig
Platform: any
Requires-Python: >=3.6
Requires-Dist: anyconfig
